{"cameraMode":{"drawMode":0,"name":"Shaded","section":"Shading Mode"},"sceneLighting":true,"audioPlay":false,"sceneViewState":{"m_AlwaysRefresh":false,"showFog":true,"showSkybox":true,"showFlares":true,"showImageEffects":true,"showParticleSystems":true,"showVisualEffectGraphs":true,"m_FxEnabled":true},"in2DMode":false,"pivot":{"x":-30.8704833984375,"y":-10.881343841552735,"z":26.033653259277345},"rotation":{"x":-0.14027753472328187,"y":0.4101767838001251,"z":-0.06401154398918152,"w":-0.8988804817199707},"size":48.20518493652344,"orthographic":false}